pytestarch/__init__.py
pytestarch/diagram_extension/__init__.py
pytestarch/diagram_extension/dependency_to_rule_converter.py
pytestarch/diagram_extension/diagram_parser.py
pytestarch/diagram_extension/diagram_rule.py
pytestarch/diagram_extension/exceptions.py
pytestarch/diagram_extension/parsed_dependencies.py
pytestarch/eval_structure/__init__.py
pytestarch/eval_structure/breadth_first_searches.py
pytestarch/eval_structure/evaluable_architecture.py
pytestarch/eval_structure/evaluable_graph.py
pytestarch/eval_structure/evaluable_structures.py
pytestarch/eval_structure/exceptions.py
pytestarch/eval_structure/module_name_converter.py
pytestarch/eval_structure/networkxgraph.py
pytestarch/eval_structure/types.py
pytestarch/eval_structure/utils.py
pytestarch/eval_structure_generation/__init__.py
pytestarch/eval_structure_generation/file_import/__init__.py
pytestarch/eval_structure_generation/file_import/config.py
pytestarch/eval_structure_generation/file_import/converter.py
pytestarch/eval_structure_generation/file_import/exceptions.py
pytestarch/eval_structure_generation/file_import/file_filter.py
pytestarch/eval_structure_generation/file_import/import_filter.py
pytestarch/eval_structure_generation/file_import/import_types.py
pytestarch/eval_structure_generation/file_import/importee_module_calculator.py
pytestarch/eval_structure_generation/file_import/parser.py
pytestarch/eval_structure_generation/graph_generation/__init__.py
pytestarch/eval_structure_generation/graph_generation/graph_generator.py
pytestarch/py.typed
pytestarch/pytestarch.py
pytestarch/query_language/LANGUAGE_DEFINTION.md
pytestarch/query_language/__init__.py
pytestarch/query_language/base_language.py
pytestarch/query_language/exceptions.py
pytestarch/query_language/layered_architecture_rule.py
pytestarch/query_language/multiple_rule_applier.py
pytestarch/query_language/rule.py
pytestarch/rule_assessment/__init__.py
pytestarch/rule_assessment/error_message/__init__.py
pytestarch-4.0.1.dist-info/LICENSE
pytestarch-4.0.1.dist-info/METADATA
pytestarch-4.0.1.dist-info/WHEEL
pytestarch-4.0.1.dist-info/RECORD
