Metadata-Version: 2.3
Name: PyTestArch
Version: 4.0.1
Summary: Test framework for software architecture based on imports between modules
License: Apache-2.0
Keywords: architecture,test
Author: zyskarch
Author-email: zyskarch@gmail.com
Maintainer: zyskarch
Maintainer-email: zyskarch@gmail.com
Requires-Python: >=3.9
Classifier: Programming Language :: Python :: 3.13
Classifier: Programming Language :: Python :: 3.12
Classifier: Programming Language :: Python :: 3.11
Classifier: Programming Language :: Python :: 3.10
Classifier: Programming Language :: Python :: 3.9
Classifier: License :: OSI Approved :: Apache Software License
Classifier: Operating System :: OS Independent
Classifier: Intended Audience :: Developers
Classifier: Topic :: Software Development :: Testing
Classifier: Topic :: Software Development :: Testing :: Unit
Provides-Extra: visualization
Requires-Dist: matplotlib (>=3.9) ; extra == "visualization"
Requires-Dist: networkx (>=3.2)
Project-URL: Documentation, https://zyskarch.github.io/pytestarch/latest
Project-URL: Repository, https://github.com/zyskarch/pytestarch
Project-URL: issues, https://github.com/zyskarch/pytestarch/issues
